{
  "5015045711486782039": {
    "id": "5015045711486782039",
    "uid": "2866653821088827850",
    "pid": "12795",
    "user_name": "贾车主",
    "avater": "//img-hxy011.didistatic.com/static/jiayou/avater.png",
    "sale_price": "10000",
    "real_price": "9800",
    "real_price_fmt": "98.00",
    "status": 0,
    "pay_time": 1529688477,
    "pay_time_fmt": "1:27",
    "car_model": "",
    "save_price": "200",
    "save_price_fmt": "2.00"
  },
  "5015064832140377812": {
    "id": "5015064832140377812",
    "uid": "4984788875822758958",
    "pid": "564018717925376",
    "user_name": "王车主",
    "avater": "//img-hxy011.didistatic.com/static/jiayou/avater.png",
    "sale_price": "20000",
    "real_price": "19300",
    "real_price_fmt": "193.00",
    "status": 0,
    "pay_time": 1529693018,
    "pay_time_fmt": "2:43",
    "car_model": "长安CS75",
    "save_price": "700",
    "save_price_fmt": "7.00"
  },
  "5015095183315304434": {
    "id": "5015095183315304434",
    "uid": "4888739751327956553",
    "pid": "580542150527515",
    "user_name": "范车主",
    "avater": "//img-hxy011.didistatic.com/static/jiayou/avater.png",
    "sale_price": "18500",
    "real_price": "17545",
    "real_price_fmt": "175.45",
    "status": 0,
    "pay_time": 1529700267,
    "pay_time_fmt": "4:44",
    "car_model": "奔腾B50",
    "save_price": "955",
    "save_price_fmt": "9.55"
  },
  "5015111601943219192": {
    "id": "5015111601943219192",
    "uid": "3315360781239060546",
    "pid": "3859436",
    "user_name": "王车主",
    "avater": "//img-hxy011.didistatic.com/static/jiayou/avater.png",
    "sale_price": "12600",
    "real_price": "12322",
    "real_price_fmt": "123.22",
    "status": 0,
    "pay_time": 1529704169,
    "pay_time_fmt": "5:49",
    "car_model": "",
    "save_price": "278",
    "save_price_fmt": "2.78"
  },
  "5015127131471219396": {
    "id": "5015127131471219396",
    "uid": "2892635056306915578",
    "pid": "564325627407387",
    "user_name": "谷车主",
    "avater": "//img-hxy011.didistatic.com/static/jiayou/avater.png",
    "sale_price": "30000",
    "real_price": "28800",
    "real_price_fmt": "288.00",
    "status": 0,
    "pay_time": 1529707873,
    "pay_time_fmt": "6:51",
    "car_model": "大众速腾",
    "save_price": "1200",
    "save_price_fmt": "12.00"
  },
  "5015131472844553303": {
    "id": "5015131472844553303",
    "uid": "4923830120709094421",
    "pid": "580542242347036",
    "user_name": "黄车主",
    "avater": "//img-hxy011.didistatic.com/static/jiayou/avater.png",
    "sale_price": "10000",
    "real_price": "9800",
    "real_price_fmt": "98.00",
    "status": 0,
    "pay_time": 1529708901,
    "pay_time_fmt": "7:08",
    "car_model": "起亚K3",
    "save_price": "200",
    "save_price_fmt": "2.00"
  },
  "5015157583418493591": {
    "id": "5015157583418493591",
    "uid": "911206917727586459",
    "pid": "563773206896643",
    "user_name": "陈车主",
    "avater": "//img-hxy011.didistatic.com/static/jiayou/avater.png",
    "sale_price": "21400",
    "real_price": "20558",
    "real_price_fmt": "205.58",
    "status": 0,
    "pay_time": 1529715155,
    "pay_time_fmt": "8:52",
    "car_model": "东南V3菱悦",
    "save_price": "842",
    "save_price_fmt": "8.42"
  },
  "5015162429198568176": {
    "id": "5015162429198568176",
    "uid": "913833459746081318",
    "pid": "563272280576002",
    "user_name": "沙车主",
    "avater": "//img-hxy011.didistatic.com/static/jiayou/avater.png",
    "sale_price": "14600",
    "real_price": "14262",
    "real_price_fmt": "142.62",
    "status": 0,
    "pay_time": 1529716291,
    "pay_time_fmt": "9:11",
    "car_model": "丰田凯美瑞",
    "save_price": "338",
    "save_price_fmt": "3.38"
  },
  "5015164089937690189": {
    "id": "5015164089937690189",
    "uid": "4955114777765215673",
    "pid": "580542283379039",
    "user_name": "王车主",
    "avater": "//img-hxy011.didistatic.com/static/jiayou/avater.png",
    "sale_price": "19300",
    "real_price": "18821",
    "real_price_fmt": "188.21",
    "status": 0,
    "pay_time": 1529716683,
    "pay_time_fmt": "9:18",
    "car_model": "东风风行CM7",
    "save_price": "479",
    "save_price_fmt": "4.79"
  },
  "5015172524368461612": {
    "id": "5015172524368461612",
    "uid": "4894751164714450840",
    "pid": "580542158805617",
    "user_name": "张车主",
    "avater": "//img-hxy011.didistatic.com/static/jiayou/avater.png",
    "sale_price": "24300",
    "real_price": "23271",
    "real_price_fmt": "232.71",
    "status": 0,
    "pay_time": 1529718695,
    "pay_time_fmt": "9:51",
    "car_model": "日产阳光",
    "save_price": "1029",
    "save_price_fmt": "10.29"
  },
  "5015176604142796133": {
    "id": "5015176604142796133",
    "uid": "4984101522259050256",
    "pid": "580542349491042",
    "user_name": "王车主",
    "avater": "//img-hxy011.didistatic.com/static/jiayou/avater.png",
    "sale_price": "17500",
    "real_price": "17075",
    "real_price_fmt": "170.75",
    "status": 0,
    "pay_time": 1529719668,
    "pay_time_fmt": "10:07",
    "car_model": "马自达3",
    "save_price": "425",
    "save_price_fmt": "4.25"
  },
  "5015179246793391187": {
    "id": "5015179246793391187",
    "uid": "1965210938617363842",
    "pid": "565490233774738",
    "user_name": "赵车主",
    "avater": "//img-hxy011.didistatic.com/static/jiayou/avater.png",
    "sale_price": "9700",
    "real_price": "9409",
    "real_price_fmt": "94.09",
    "status": 0,
    "pay_time": 1529720313,
    "pay_time_fmt": "10:18",
    "car_model": "大众朗逸",
    "save_price": "291",
    "save_price_fmt": "2.91"
  },
  "5015179782955465780": {
    "id": "5015179782955465780",
    "uid": "1935126737583079100",
    "pid": "565460470472887",
    "user_name": "马车主",
    "avater": "//img-hxy011.didistatic.com/static/jiayou/avater.png",
    "sale_price": "20000",
    "real_price": "19100",
    "real_price_fmt": "191.00",
    "status": 0,
    "pay_time": 1529720421,
    "pay_time_fmt": "10:20",
    "car_model": "日产轩逸",
    "save_price": "900",
    "save_price_fmt": "9.00"
  },
  "5015180323621964375": {
    "id": "5015180323621964375",
    "uid": "3482647234930281355",
    "pid": "567950059089318",
    "user_name": "王车主",
    "avater": "//img-hxy011.didistatic.com/static/jiayou/avater.png",
    "sale_price": "20000",
    "real_price": "19100",
    "real_price_fmt": "191.00",
    "status": 0,
    "pay_time": 1529720566,
    "pay_time_fmt": "10:22",
    "car_model": "雪佛兰迈锐宝",
    "save_price": "900",
    "save_price_fmt": "9.00"
  },
  "5015190427264351552": {
    "id": "5015190427264351552",
    "uid": "4985958302706564812",
    "pid": "565542666118053",
    "user_name": "余车主",
    "avater": "//img-hxy011.didistatic.com/static/jiayou/avater.png",
    "sale_price": "28200",
    "real_price": "27054",
    "real_price_fmt": "270.54",
    "status": 0,
    "pay_time": 1529722963,
    "pay_time_fmt": "11:02",
    "car_model": "丰田雷凌",
    "save_price": "1146",
    "save_price_fmt": "11.46"
  },
  "5015198018555873361": {
    "id": "5015198018555873361",
    "uid": "3089692042524363703",
    "pid": "566151900175421",
    "user_name": "陈车主",
    "avater": "//img-hxy011.didistatic.com/static/jiayou/avater.png",
    "sale_price": "20500",
    "real_price": "19585",
    "real_price_fmt": "195.85",
    "status": 0,
    "pay_time": 1529724764,
    "pay_time_fmt": "11:32",
    "car_model": "",
    "save_price": "915",
    "save_price_fmt": "9.15"
  },
  "5015198311444122156": {
    "id": "5015198311444122156",
    "uid": "910894475164256953",
    "pid": "563543217147906",
    "user_name": "卢车主",
    "avater": "//img-hxy011.didistatic.com/static/jiayou/avater.png",
    "sale_price": "22500",
    "real_price": "21625",
    "real_price_fmt": "216.25",
    "status": 0,
    "pay_time": 1529724841,
    "pay_time_fmt": "11:34",
    "car_model": "现代悦动",
    "save_price": "875",
    "save_price_fmt": "8.75"
  },
  "5015198671952939321": {
    "id": "5015198671952939321",
    "uid": "911224436764969364",
    "pid": "563564124831744",
    "user_name": "高车主",
    "avater": "//img-hxy011.didistatic.com/static/jiayou/avater.png",
    "sale_price": "10000",
    "real_price": "9800",
    "real_price_fmt": "98.00",
    "status": 0,
    "pay_time": 1529724926,
    "pay_time_fmt": "11:35",
    "car_model": "标致408",
    "save_price": "200",
    "save_price_fmt": "2.00"
  },
  "5015200773844502871": {
    "id": "5015200773844502871",
    "uid": "4877164802100955888",
    "pid": "5000236691854",
    "user_name": "刘车主",
    "avater": "//img-hxy011.didistatic.com/static/jiayou/avater.png",
    "sale_price": "16100",
    "real_price": "15717",
    "real_price_fmt": "157.17",
    "status": 0,
    "pay_time": 1529725428,
    "pay_time_fmt": "11:43",
    "car_model": "",
    "save_price": "383",
    "save_price_fmt": "3.83"
  },
  "5015224496412691048": {
    "id": "5015224496412691048",
    "uid": "3692604701553199109",
    "pid": "105758",
    "user_name": "刘车主",
    "avater": "//img-hxy011.didistatic.com/static/jiayou/avater.png",
    "sale_price": "16100",
    "real_price": "15717",
    "real_price_fmt": "157.17",
    "status": 0,
    "pay_time": 1529731091,
    "pay_time_fmt": "13:18",
    "car_model": "",
    "save_price": "383",
    "save_price_fmt": "3.83"
  }
}