{
  "5015171952139324406": {
    "id": "5015171952139324406",
    "uid": "4917155944384187187",
    "pid": "283186834314661",
    "user_name": "万车主",
    "avater": "//img-hxy011.didistatic.com/static/jiayou/avater.png",
    "sale_price": "20000",
    "real_price": "19100",
    "real_price_fmt": "191.00",
    "status": 0,
    "pay_time": 1529718555,
    "pay_time_fmt": "9:49",
    "car_model": "",
    "save_price": "900",
    "save_price_fmt": "9.00"
  },
  "5015174374274386326": {
    "id": "5015174374274386326",
    "uid": "2237170566195071182",
    "pid": "565740113571082",
    "user_name": "彭车主",
    "avater": "//img-hxy011.didistatic.com/static/jiayou/avater.png",
    "sale_price": "10000",
    "real_price": "9600",
    "real_price_fmt": "96.00",
    "status": 0,
    "pay_time": 1529719133,
    "pay_time_fmt": "9:58",
    "car_model": "现代瑞纳",
    "save_price": "400",
    "save_price_fmt": "4.00"
  },
  "5015174801292525346": {
    "id": "5015174801292525346",
    "uid": "4898608666820476343",
    "pid": "286475137709899",
    "user_name": "曾车主",
    "avater": "//img-hxy011.didistatic.com/static/jiayou/avater.png",
    "sale_price": "21000",
    "real_price": "20050",
    "real_price_fmt": "200.50",
    "status": 0,
    "pay_time": 1529719238,
    "pay_time_fmt": "10:00",
    "car_model": "",
    "save_price": "950",
    "save_price_fmt": "9.50"
  },
  "5015181322524838012": {
    "id": "5015181322524838012",
    "uid": "2873266829143591677",
    "pid": "565409838535483",
    "user_name": "杨车主",
    "avater": "//img-hxy011.didistatic.com/static/jiayou/avater.png",
    "sale_price": "20000",
    "real_price": "18800",
    "real_price_fmt": "188.00",
    "status": 0,
    "pay_time": 1529720788,
    "pay_time_fmt": "10:26",
    "car_model": "大众帕萨特",
    "save_price": "1200",
    "save_price_fmt": "12.00"
  },
  "5015181386131458712": {
    "id": "5015181386131458712",
    "uid": "3680113929285290696",
    "pid": "567950094305635",
    "user_name": "罗车主",
    "avater": "//img-hxy011.didistatic.com/static/jiayou/avater.png",
    "sale_price": "10000",
    "real_price": "9400",
    "real_price_fmt": "94.00",
    "status": 0,
    "pay_time": 1529720800,
    "pay_time_fmt": "10:26",
    "car_model": "雪铁龙C4L",
    "save_price": "600",
    "save_price_fmt": "6.00"
  },
  "5015182046595926726": {
    "id": "5015182046595926726",
    "uid": "4974791593647687940",
    "pid": "282610445393922",
    "user_name": "刘车主",
    "avater": "//img-hxy011.didistatic.com/static/jiayou/avater.png",
    "sale_price": "10000",
    "real_price": "9600",
    "real_price_fmt": "96.00",
    "status": 0,
    "pay_time": 1529720965,
    "pay_time_fmt": "10:29",
    "car_model": "",
    "save_price": "400",
    "save_price_fmt": "4.00"
  },
  "5015182696088337735": {
    "id": "5015182696088337735",
    "uid": "4888713368103026196",
    "pid": "565597089045674",
    "user_name": "马车主",
    "avater": "//img-hxy011.didistatic.com/static/jiayou/avater.png",
    "sale_price": "27300",
    "real_price": "26035",
    "real_price_fmt": "260.35",
    "status": 0,
    "pay_time": 1529721183,
    "pay_time_fmt": "10:33",
    "car_model": "大众宝来",
    "save_price": "1265",
    "save_price_fmt": "12.65"
  },
  "5015183350932438129": {
    "id": "5015183350932438129",
    "uid": "4991031376367845009",
    "pid": "580542292416060",
    "user_name": "杨车主",
    "avater": "//img-hxy011.didistatic.com/static/jiayou/avater.png",
    "sale_price": "36000",
    "real_price": "34300",
    "real_price_fmt": "343.00",
    "status": 0,
    "pay_time": 1529721270,
    "pay_time_fmt": "10:34",
    "car_model": "大众新桑塔纳",
    "save_price": "1700",
    "save_price_fmt": "17.00"
  },
  "5015185440069123171": {
    "id": "5015185440069123171",
    "uid": "2170568602841775428",
    "pid": "283130843039656",
    "user_name": "仲车主",
    "avater": "//img-hxy011.didistatic.com/static/jiayou/avater.png",
    "sale_price": "20000",
    "real_price": "19100",
    "real_price_fmt": "191.00",
    "status": 0,
    "pay_time": 1529721776,
    "pay_time_fmt": "10:42",
    "car_model": "丰田汉兰达",
    "save_price": "900",
    "save_price_fmt": "9.00"
  },
  "5015187395260467724": {
    "id": "5015187395260467724",
    "uid": "910822888662648984",
    "pid": "563790997749763",
    "user_name": "张车主",
    "avater": "//img-hxy011.didistatic.com/static/jiayou/avater.png",
    "sale_price": "30000",
    "real_price": "27800",
    "real_price_fmt": "278.00",
    "status": 0,
    "pay_time": 1529722235,
    "pay_time_fmt": "10:50",
    "car_model": "大众凌渡",
    "save_price": "2200",
    "save_price_fmt": "22.00"
  },
  "5015191312962702062": {
    "id": "5015191312962702062",
    "uid": "4871824172709595552",
    "pid": "567950130142895",
    "user_name": "程车主",
    "avater": "//img-hxy011.didistatic.com/static/jiayou/avater.png",
    "sale_price": "20000",
    "real_price": "18700",
    "real_price_fmt": "187.00",
    "status": 0,
    "pay_time": 1529723869,
    "pay_time_fmt": "11:17",
    "car_model": "雪佛兰乐风RV",
    "save_price": "1300",
    "save_price_fmt": "13.00"
  },
  "5015192516468145576": {
    "id": "5015192516468145576",
    "uid": "4998969310735761129",
    "pid": "580542324529200",
    "user_name": "陈车主",
    "avater": "//img-hxy011.didistatic.com/static/jiayou/avater.png",
    "sale_price": "35200",
    "real_price": "33140",
    "real_price_fmt": "331.40",
    "status": 0,
    "pay_time": 1529723457,
    "pay_time_fmt": "11:10",
    "car_model": "标致308",
    "save_price": "2060",
    "save_price_fmt": "20.60"
  },
  "5015194445151731682": {
    "id": "5015194445151731682",
    "uid": "4897079287405608829",
    "pid": "283062031160163",
    "user_name": "张车主",
    "avater": "//img-hxy011.didistatic.com/static/jiayou/avater.png",
    "sale_price": "20000",
    "real_price": "19100",
    "real_price_fmt": "191.00",
    "status": 0,
    "pay_time": 1529723916,
    "pay_time_fmt": "11:18",
    "car_model": "标致408",
    "save_price": "900",
    "save_price_fmt": "9.00"
  },
  "5015195461964266937": {
    "id": "5015195461964266937",
    "uid": "4916257505127693773",
    "pid": "580542236764358",
    "user_name": "张车主",
    "avater": "//img-hxy011.didistatic.com/static/jiayou/avater.png",
    "sale_price": "26000",
    "real_price": "24400",
    "real_price_fmt": "244.00",
    "status": 0,
    "pay_time": 1529724165,
    "pay_time_fmt": "11:22",
    "car_model": "大众高尔夫",
    "save_price": "1600",
    "save_price_fmt": "16.00"
  },
  "5015198014957177166": {
    "id": "5015198014957177166",
    "uid": "4960162410736928845",
    "pid": "284365118442124",
    "user_name": "黄车主",
    "avater": "//img-hxy011.didistatic.com/static/jiayou/avater.png",
    "sale_price": "20000",
    "real_price": "18600",
    "real_price_fmt": "186.00",
    "status": 0,
    "pay_time": 1529724786,
    "pay_time_fmt": "11:33",
    "car_model": "",
    "save_price": "1400",
    "save_price_fmt": "14.00"
  },
  "5015202106119047620": {
    "id": "5015202106119047620",
    "uid": "3730672716429412702",
    "pid": "299067184487825",
    "user_name": "刘车主",
    "avater": "//img-hxy011.didistatic.com/static/jiayou/avater.png",
    "sale_price": "19000",
    "real_price": "18150",
    "real_price_fmt": "181.50",
    "status": 0,
    "pay_time": 1529725748,
    "pay_time_fmt": "11:49",
    "car_model": "",
    "save_price": "850",
    "save_price_fmt": "8.50"
  },
  "5015203166409739050": {
    "id": "5015203166409739050",
    "uid": "3534862431778261472",
    "pid": "565631081585366",
    "user_name": "段车主",
    "avater": "//img-hxy011.didistatic.com/static/jiayou/avater.png",
    "sale_price": "15000",
    "real_price": "14350",
    "real_price_fmt": "143.50",
    "status": 0,
    "pay_time": 1529725990,
    "pay_time_fmt": "11:53",
    "car_model": "长安逸动",
    "save_price": "650",
    "save_price_fmt": "6.50"
  },
  "5015203455502142062": {
    "id": "5015203455502142062",
    "uid": "911175314821367985",
    "pid": "563679275257856",
    "user_name": "刘车主",
    "avater": "//img-hxy011.didistatic.com/static/jiayou/avater.png",
    "sale_price": "30600",
    "real_price": "28670",
    "real_price_fmt": "286.70",
    "status": 0,
    "pay_time": 1529726070,
    "pay_time_fmt": "11:54",
    "car_model": "",
    "save_price": "1930",
    "save_price_fmt": "19.30"
  },
  "5015204756885621158": {
    "id": "5015204756885621158",
    "uid": "4920561085669984799",
    "pid": "282847841166491",
    "user_name": "黄车主",
    "avater": "//img-hxy011.didistatic.com/static/jiayou/avater.png",
    "sale_price": "25100",
    "real_price": "23945",
    "real_price_fmt": "239.45",
    "status": 0,
    "pay_time": 1529726373,
    "pay_time_fmt": "11:59",
    "car_model": "宝马7系",
    "save_price": "1155",
    "save_price_fmt": "11.55"
  },
  "5015213020948200590": {
    "id": "5015213020948200590",
    "uid": "4926836641340587852",
    "pid": "580542255108309",
    "user_name": "邓车主",
    "avater": "//img-hxy011.didistatic.com/static/jiayou/avater.png",
    "sale_price": "25800",
    "real_price": "23810",
    "real_price_fmt": "238.10",
    "status": 0,
    "pay_time": 1529728346,
    "pay_time_fmt": "12:32",
    "car_model": "大众朗行",
    "save_price": "1990",
    "save_price_fmt": "19.90"
  }
}