{
  "282120256880641": {
    "driver_id": "282120256880641",
    "avanter": "//img-hxy011.didistatic.com/static/jiayou/avater.png",
    "driver_name": "张车主",
    "user_name": "张车主",
    "car_model": "",
    "order_count_1m": 13,
    "ordercount_1m": 13,
    "order_discount_1m_fmt": "204.82"
  },
  "283130899406738": {
    "driver_id": "283130899406738",
    "avanter": "//img-hxy011.didistatic.com/static/jiayou/avater.png",
    "driver_name": "李车主",
    "user_name": "李车主",
    "car_model": "",
    "order_count_1m": 8,
    "ordercount_1m": 8,
    "order_discount_1m_fmt": "115.82"
  },
  "284530402922197": {
    "driver_id": "284530402922197",
    "avanter": "//img-hxy011.didistatic.com/static/jiayou/avater.png",
    "driver_name": "田车主",
    "user_name": "田车主",
    "car_model": "",
    "order_count_1m": 9,
    "ordercount_1m": 9,
    "order_discount_1m_fmt": "126.71"
  },
  "284886755579069": {
    "driver_id": "284886755579069",
    "avanter": "//img-hxy011.didistatic.com/static/jiayou/avater.png",
    "driver_name": "曾车主",
    "user_name": "曾车主",
    "car_model": "",
    "order_count_1m": 13,
    "ordercount_1m": 13,
    "order_discount_1m_fmt": "202.43"
  },
  "563611635875841": {
    "driver_id": "563611635875841",
    "avanter": "//img-hxy011.didistatic.com/static/jiayou/avater.png",
    "driver_name": "张车主",
    "user_name": "张车主",
    "car_model": "丰田卡罗拉",
    "order_count_1m": 12,
    "ordercount_1m": 12,
    "order_discount_1m_fmt": "80.84"
  },
  "563802016653312": {
    "driver_id": "563802016653312",
    "avanter": "//img-hxy011.didistatic.com/static/jiayou/avater.png",
    "driver_name": "李车主",
    "user_name": "李车主",
    "car_model": "起亚K4",
    "order_count_1m": 8,
    "ordercount_1m": 8,
    "order_discount_1m_fmt": "205.10"
  },
  "563848580562947": {
    "driver_id": "563848580562947",
    "avanter": "//img-hxy011.didistatic.com/static/jiayou/avater.png",
    "driver_name": "严车主",
    "user_name": "严车主",
    "car_model": "哈弗H6",
    "order_count_1m": 14,
    "ordercount_1m": 14,
    "order_discount_1m_fmt": "353.36"
  },
  "563883616509953": {
    "driver_id": "563883616509953",
    "avanter": "//img-hxy011.didistatic.com/static/jiayou/avater.png",
    "driver_name": "邓车主",
    "user_name": "邓车主",
    "car_model": "雪佛兰赛欧",
    "order_count_1m": 17,
    "ordercount_1m": 17,
    "order_discount_1m_fmt": "411.73"
  },
  "563991107215362": {
    "driver_id": "563991107215362",
    "avanter": "//img-hxy011.didistatic.com/static/jiayou/avater.png",
    "driver_name": "胡车主",
    "user_name": "胡车主",
    "car_model": "雪铁龙爱丽舍",
    "order_count_1m": 9,
    "ordercount_1m": 9,
    "order_discount_1m_fmt": "165.69"
  },
  "564187120734209": {
    "driver_id": "564187120734209",
    "avanter": "//img-hxy011.didistatic.com/static/jiayou/avater.png",
    "driver_name": "钟车主",
    "user_name": "钟车主",
    "car_model": "标致308",
    "order_count_1m": 14,
    "ordercount_1m": 14,
    "order_discount_1m_fmt": "157.00"
  },
  "564256312922113": {
    "driver_id": "564256312922113",
    "avanter": "//img-hxy011.didistatic.com/static/jiayou/avater.png",
    "driver_name": "雷车主",
    "user_name": "雷车主",
    "car_model": "日产轩逸",
    "order_count_1m": 11,
    "ordercount_1m": 11,
    "order_discount_1m_fmt": "238.31"
  },
  "564302910590977": {
    "driver_id": "564302910590977",
    "avanter": "//img-hxy011.didistatic.com/static/jiayou/avater.png",
    "driver_name": "凌车主",
    "user_name": "凌车主",
    "car_model": "铃木启悦",
    "order_count_1m": 8,
    "ordercount_1m": 8,
    "order_discount_1m_fmt": "196.35"
  },
  "564316638218039": {
    "driver_id": "564316638218039",
    "avanter": "//img-hxy011.didistatic.com/static/jiayou/avater.png",
    "driver_name": "龙车主",
    "user_name": "龙车主",
    "car_model": "标致207(进口)",
    "order_count_1m": 13,
    "ordercount_1m": 13,
    "order_discount_1m_fmt": "189.62"
  },
  "564419264781882": {
    "driver_id": "564419264781882",
    "avanter": "//img-hxy011.didistatic.com/static/jiayou/avater.png",
    "driver_name": "黄车主",
    "user_name": "黄车主",
    "car_model": "雪铁龙C5",
    "order_count_1m": 11,
    "ordercount_1m": 11,
    "order_discount_1m_fmt": "310.62"
  },
  "564419827337722": {
    "driver_id": "564419827337722",
    "avanter": "//img-hxy011.didistatic.com/static/jiayou/avater.png",
    "driver_name": "何车主",
    "user_name": "何车主",
    "car_model": "比亚迪秦",
    "order_count_1m": 9,
    "ordercount_1m": 9,
    "order_discount_1m_fmt": "135.23"
  },
  "564817462758052": {
    "driver_id": "564817462758052",
    "avanter": "//img-hxy011.didistatic.com/static/jiayou/avater.png",
    "driver_name": "尹车主",
    "user_name": "尹车主",
    "car_model": "长城C50",
    "order_count_1m": 26,
    "ordercount_1m": 26,
    "order_discount_1m_fmt": "315.79"
  },
  "564936452090742": {
    "driver_id": "564936452090742",
    "avanter": "//img-hxy011.didistatic.com/static/jiayou/avater.png",
    "driver_name": "彭车主",
    "user_name": "彭车主",
    "car_model": "丰田卡罗拉",
    "order_count_1m": 9,
    "ordercount_1m": 9,
    "order_discount_1m_fmt": "132.30"
  },
  "565041213479459": {
    "driver_id": "565041213479459",
    "avanter": "//img-hxy011.didistatic.com/static/jiayou/avater.png",
    "driver_name": "刘车主",
    "user_name": "刘车主",
    "car_model": "本田杰德",
    "order_count_1m": 12,
    "ordercount_1m": 12,
    "order_discount_1m_fmt": "189.44"
  },
  "565163689453387": {
    "driver_id": "565163689453387",
    "avanter": "//img-hxy011.didistatic.com/static/jiayou/avater.png",
    "driver_name": "杨车主",
    "user_name": "杨车主",
    "car_model": "长安CX70",
    "order_count_1m": 9,
    "ordercount_1m": 9,
    "order_discount_1m_fmt": "193.34"
  },
  "565228577167617": {
    "driver_id": "565228577167617",
    "avanter": "//img-hxy011.didistatic.com/static/jiayou/avater.png",
    "driver_name": "毛车主",
    "user_name": "毛车主",
    "car_model": "雪佛兰爱唯欧",
    "order_count_1m": 8,
    "ordercount_1m": 8,
    "order_discount_1m_fmt": "115.81"
  },
  "565240256532476": {
    "driver_id": "565240256532476",
    "avanter": "//img-hxy011.didistatic.com/static/jiayou/avater.png",
    "driver_name": "史车主",
    "user_name": "史车主",
    "car_model": "大众新捷达",
    "order_count_1m": 8,
    "ordercount_1m": 8,
    "order_discount_1m_fmt": "216.56"
  },
  "565326165180445": {
    "driver_id": "565326165180445",
    "avanter": "//img-hxy011.didistatic.com/static/jiayou/avater.png",
    "driver_name": "刘车主",
    "user_name": "刘车主",
    "car_model": "丰田雷凌双擎",
    "order_count_1m": 10,
    "ordercount_1m": 10,
    "order_discount_1m_fmt": "198.50"
  },
  "565423416804148": {
    "driver_id": "565423416804148",
    "avanter": "//img-hxy011.didistatic.com/static/jiayou/avater.png",
    "driver_name": "赵车主",
    "user_name": "赵车主",
    "car_model": "大众凌渡",
    "order_count_1m": 9,
    "ordercount_1m": 9,
    "order_discount_1m_fmt": "181.64"
  },
  "565634814649596": {
    "driver_id": "565634814649596",
    "avanter": "//img-hxy011.didistatic.com/static/jiayou/avater.png",
    "driver_name": "邹车主",
    "user_name": "邹车主",
    "car_model": "北汽绅宝X35",
    "order_count_1m": 10,
    "ordercount_1m": 10,
    "order_discount_1m_fmt": "129.40"
  },
  "565829857323400": {
    "driver_id": "565829857323400",
    "avanter": "//img-hxy011.didistatic.com/static/jiayou/avater.png",
    "driver_name": "严车主",
    "user_name": "严车主",
    "car_model": "雪铁龙爱丽舍",
    "order_count_1m": 10,
    "ordercount_1m": 10,
    "order_discount_1m_fmt": "162.64"
  },
  "565947190804855": {
    "driver_id": "565947190804855",
    "avanter": "//img-hxy011.didistatic.com/static/jiayou/avater.png",
    "driver_name": "王车主",
    "user_name": "王车主",
    "car_model": "福特福睿斯",
    "order_count_1m": 12,
    "ordercount_1m": 12,
    "order_discount_1m_fmt": "268.06"
  },
  "565977387508142": {
    "driver_id": "565977387508142",
    "avanter": "//img-hxy011.didistatic.com/static/jiayou/avater.png",
    "driver_name": "毛车主",
    "user_name": "毛车主",
    "car_model": "起亚K3",
    "order_count_1m": 9,
    "ordercount_1m": 9,
    "order_discount_1m_fmt": "161.09"
  },
  "566024353548075": {
    "driver_id": "566024353548075",
    "avanter": "//img-hxy011.didistatic.com/static/jiayou/avater.png",
    "driver_name": "江车主",
    "user_name": "江车主",
    "car_model": "福特福克斯",
    "order_count_1m": 10,
    "ordercount_1m": 10,
    "order_discount_1m_fmt": "319.90"
  },
  "566108030838305": {
    "driver_id": "566108030838305",
    "avanter": "//img-hxy011.didistatic.com/static/jiayou/avater.png",
    "driver_name": "陈车主",
    "user_name": "陈车主",
    "car_model": "现代名图",
    "order_count_1m": 11,
    "ordercount_1m": 11,
    "order_discount_1m_fmt": "257.85"
  },
  "566254369317661": {
    "driver_id": "566254369317661",
    "avanter": "//img-hxy011.didistatic.com/static/jiayou/avater.png",
    "driver_name": "邓车主",
    "user_name": "邓车主",
    "car_model": "起亚KX3",
    "order_count_1m": 9,
    "ordercount_1m": 9,
    "order_discount_1m_fmt": "103.70"
  },
  "566459423392521": {
    "driver_id": "566459423392521",
    "avanter": "//img-hxy011.didistatic.com/static/jiayou/avater.png",
    "driver_name": "张车主",
    "user_name": "张车主",
    "car_model": "日产轩逸",
    "order_count_1m": 20,
    "ordercount_1m": 20,
    "order_discount_1m_fmt": "356.38"
  },
  "567949993987266": {
    "driver_id": "567949993987266",
    "avanter": "//img-hxy011.didistatic.com/static/jiayou/avater.png",
    "driver_name": "彭车主",
    "user_name": "彭车主",
    "car_model": "雪铁龙爱丽舍",
    "order_count_1m": 11,
    "ordercount_1m": 11,
    "order_discount_1m_fmt": "234.49"
  },
  "567950107323920": {
    "driver_id": "567950107323920",
    "avanter": "//img-hxy011.didistatic.com/static/jiayou/avater.png",
    "driver_name": "戴车主",
    "user_name": "戴车主",
    "car_model": "本田凌派",
    "order_count_1m": 10,
    "ordercount_1m": 10,
    "order_discount_1m_fmt": "97.37"
  },
  "580542170052187": {
    "driver_id": "580542170052187",
    "avanter": "//img-hxy011.didistatic.com/static/jiayou/avater.png",
    "driver_name": "刘车主",
    "user_name": "刘车主",
    "car_model": "中华H330",
    "order_count_1m": 11,
    "ordercount_1m": 11,
    "order_discount_1m_fmt": "110.72"
  },
  "580542171130071": {
    "driver_id": "580542171130071",
    "avanter": "//img-hxy011.didistatic.com/static/jiayou/avater.png",
    "driver_name": "杨车主",
    "user_name": "杨车主",
    "car_model": "起亚K3",
    "order_count_1m": 9,
    "ordercount_1m": 9,
    "order_discount_1m_fmt": "217.81"
  },
  "580542220026672": {
    "driver_id": "580542220026672",
    "avanter": "//img-hxy011.didistatic.com/static/jiayou/avater.png",
    "driver_name": "李车主",
    "user_name": "李车主",
    "car_model": "大众凌渡",
    "order_count_1m": 11,
    "ordercount_1m": 11,
    "order_discount_1m_fmt": "197.77"
  },
  "580542252203174": {
    "driver_id": "580542252203174",
    "avanter": "//img-hxy011.didistatic.com/static/jiayou/avater.png",
    "driver_name": "杨车主",
    "user_name": "杨车主",
    "car_model": "大众朗逸",
    "order_count_1m": 11,
    "ordercount_1m": 11,
    "order_discount_1m_fmt": "219.98"
  },
  "580542252965268": {
    "driver_id": "580542252965268",
    "avanter": "//img-hxy011.didistatic.com/static/jiayou/avater.png",
    "driver_name": "刘车主",
    "user_name": "刘车主",
    "car_model": "丰田威驰",
    "order_count_1m": 8,
    "ordercount_1m": 8,
    "order_discount_1m_fmt": "108.37"
  },
  "580542266259819": {
    "driver_id": "580542266259819",
    "avanter": "//img-hxy011.didistatic.com/static/jiayou/avater.png",
    "driver_name": "周车主",
    "user_name": "周车主",
    "car_model": "长安逸动",
    "order_count_1m": 9,
    "ordercount_1m": 9,
    "order_discount_1m_fmt": "172.35"
  },
  "580542267565421": {
    "driver_id": "580542267565421",
    "avanter": "//img-hxy011.didistatic.com/static/jiayou/avater.png",
    "driver_name": "金车主",
    "user_name": "金车主",
    "car_model": "大众宝来",
    "order_count_1m": 9,
    "ordercount_1m": 9,
    "order_discount_1m_fmt": "214.30"
  },
  "580542273237813": {
    "driver_id": "580542273237813",
    "avanter": "//img-hxy011.didistatic.com/static/jiayou/avater.png",
    "driver_name": "斯车主",
    "user_name": "斯车主",
    "car_model": "丰田卡罗拉",
    "order_count_1m": 8,
    "ordercount_1m": 8,
    "order_discount_1m_fmt": "168.33"
  },
  "580542337974959": {
    "driver_id": "580542337974959",
    "avanter": "//img-hxy011.didistatic.com/static/jiayou/avater.png",
    "driver_name": "唐车主",
    "user_name": "唐车主",
    "car_model": "雪铁龙C3XR",
    "order_count_1m": 10,
    "ordercount_1m": 10,
    "order_discount_1m_fmt": "106.80"
  },
  "580542341192793": {
    "driver_id": "580542341192793",
    "avanter": "//img-hxy011.didistatic.com/static/jiayou/avater.png",
    "driver_name": "廖车主",
    "user_name": "廖车主",
    "car_model": "起亚K3",
    "order_count_1m": 17,
    "ordercount_1m": 17,
    "order_discount_1m_fmt": "284.57"
  },
  "580542393344100": {
    "driver_id": "580542393344100",
    "avanter": "//img-hxy011.didistatic.com/static/jiayou/avater.png",
    "driver_name": "张车主",
    "user_name": "张车主",
    "car_model": "众泰Z500",
    "order_count_1m": 9,
    "ordercount_1m": 9,
    "order_discount_1m_fmt": "93.20"
  },
  "580542398803079": {
    "driver_id": "580542398803079",
    "avanter": "//img-hxy011.didistatic.com/static/jiayou/avater.png",
    "driver_name": "张车主",
    "user_name": "张车主",
    "car_model": "大众帕萨特",
    "order_count_1m": 8,
    "ordercount_1m": 8,
    "order_discount_1m_fmt": "173.40"
  },
  "580542414976570": {
    "driver_id": "580542414976570",
    "avanter": "//img-hxy011.didistatic.com/static/jiayou/avater.png",
    "driver_name": "姚车主",
    "user_name": "姚车主",
    "car_model": "雪铁龙C3XR",
    "order_count_1m": 12,
    "ordercount_1m": 12,
    "order_discount_1m_fmt": "320.79"
  },
  "580542421261795": {
    "driver_id": "580542421261795",
    "avanter": "//img-hxy011.didistatic.com/static/jiayou/avater.png",
    "driver_name": "王车主",
    "user_name": "王车主",
    "car_model": "海马福美来",
    "order_count_1m": 9,
    "ordercount_1m": 9,
    "order_discount_1m_fmt": "145.74"
  },
  "580542423480760": {
    "driver_id": "580542423480760",
    "avanter": "//img-hxy011.didistatic.com/static/jiayou/avater.png",
    "driver_name": "杨车主",
    "user_name": "杨车主",
    "car_model": "起亚K2",
    "order_count_1m": 19,
    "ordercount_1m": 19,
    "order_discount_1m_fmt": "194.36"
  },
  "580542426904097": {
    "driver_id": "580542426904097",
    "avanter": "//img-hxy011.didistatic.com/static/jiayou/avater.png",
    "driver_name": "罗车主",
    "user_name": "罗车主",
    "car_model": "奔腾B30",
    "order_count_1m": 13,
    "ordercount_1m": 13,
    "order_discount_1m_fmt": "164.20"
  },
  "580542429506279": {
    "driver_id": "580542429506279",
    "avanter": "//img-hxy011.didistatic.com/static/jiayou/avater.png",
    "driver_name": "李车主",
    "user_name": "李车主",
    "car_model": "起亚K3",
    "order_count_1m": 10,
    "ordercount_1m": 10,
    "order_discount_1m_fmt": "168.92"
  }
}